README.md
setup.py
apm/APMAgent.py
apm/__init__.py
jobsimi_apm_python.egg-info/PKG-INFO
jobsimi_apm_python.egg-info/SOURCES.txt
jobsimi_apm_python.egg-info/dependency_links.txt
jobsimi_apm_python.egg-info/requires.txt
jobsimi_apm_python.egg-info/top_level.txt